calculator_package/__init__.py
shaelander_calculator-0.1.dist-info/LICENCE.txt
shaelander_calculator-0.1.dist-info/METADATA
shaelander_calculator-0.1.dist-info/WHEEL
shaelander_calculator-0.1.dist-info/top_level.txt
shaelander_calculator-0.1.dist-info/RECORD
