Metadata-Version: 2.1
Name: shaelander-calculator
Version: 0.1
Summary: This is stat to practice python packages not for any use just for testing purpose
Home-page: UNKNOWN
Author: shaelander
Author-email: sherryupsc@gmail.com
License: UNKNOWN
Platform: UNKNOWN
Classifier: Programming Language :: Python :: 3
Classifier: License :: OSI Approved :: MIT License
Classifier: Operating System :: OS Independent
